quom/__init__.py
quom/__main__.py
quom/quom.py
quom/quom_error.py
quom/tokenizer/__init__.py
quom/tokenizer/comment_tokenizer.py
quom/tokenizer/iterator.py
quom/tokenizer/number_tokenizer.py
quom/tokenizer/preprocessor_tokenizer.py
quom/tokenizer/quote_tokenizer.py
quom/tokenizer/remaining_tokenizer.py
quom/tokenizer/token.py
quom/tokenizer/tokenize.py
quom/tokenizer/tokenize_error.py
quom/tokenizer/whitespace_tokenizer.py
quom-4.0.2.dist-info/LICENSE
quom-4.0.2.dist-info/METADATA
quom-4.0.2.dist-info/WHEEL
quom-4.0.2.dist-info/entry_points.txt
quom-4.0.2.dist-info/top_level.txt
quom-4.0.2.dist-info/RECORD
