Metadata-Version: 2.1
Name: quom
Version: 4.0.2
Summary: Quom is a single header generator for C/C++ libraries.
Home-page: https://github.com/Viatorus/quom
Author: Toni Neubert
Author-email: lutztonineubert@gmail.com
License: MIT
Project-URL: Source, https://github.com/Viatorus/quom
Platform: any
Classifier: Development Status :: 5 - Production/Stable
Classifier: Topic :: Software Development :: Build Tools
Classifier: License :: OSI Approved :: MIT License
Classifier: Programming Language :: Python
Requires-Python: >=3.7
License-File: LICENSE
Requires-Dist: importlib-metadata; python_version < "3.8"
Provides-Extra: testing
Requires-Dist: pytest; extra == "testing"
Requires-Dist: pyfakefs; extra == "testing"
Requires-Dist: pytest-cov; extra == "testing"
Requires-Dist: flake8; extra == "testing"
Requires-Dist: flake8-quotes; extra == "testing"
